README.rst
pyproject.toml
setup.cfg
setup.py
/home/joshua/tmp/plastid-upload/plastid/kent/src/htslib/bgzf.c
/home/joshua/tmp/plastid-upload/plastid/kent/src/htslib/faidx.c
/home/joshua/tmp/plastid-upload/plastid/kent/src/htslib/hfile.c
/home/joshua/tmp/plastid-upload/plastid/kent/src/htslib/hfile_net.c
/home/joshua/tmp/plastid-upload/plastid/kent/src/htslib/hts.c
/home/joshua/tmp/plastid-upload/plastid/kent/src/htslib/knetfile.c
/home/joshua/tmp/plastid-upload/plastid/kent/src/htslib/kstring.c
/home/joshua/tmp/plastid-upload/plastid/kent/src/htslib/md5.c
/home/joshua/tmp/plastid-upload/plastid/kent/src/htslib/sam.c
/home/joshua/tmp/plastid-upload/plastid/kent/src/htslib/tbx.c
/home/joshua/tmp/plastid-upload/plastid/kent/src/htslib/cram/cram_codecs.c
/home/joshua/tmp/plastid-upload/plastid/kent/src/htslib/cram/cram_decode.c
/home/joshua/tmp/plastid-upload/plastid/kent/src/htslib/cram/cram_encode.c
/home/joshua/tmp/plastid-upload/plastid/kent/src/htslib/cram/cram_index.c
/home/joshua/tmp/plastid-upload/plastid/kent/src/htslib/cram/cram_io.c
/home/joshua/tmp/plastid-upload/plastid/kent/src/htslib/cram/cram_samtools.c
/home/joshua/tmp/plastid-upload/plastid/kent/src/htslib/cram/cram_stats.c
/home/joshua/tmp/plastid-upload/plastid/kent/src/htslib/cram/files.c
/home/joshua/tmp/plastid-upload/plastid/kent/src/htslib/cram/mFILE.c
/home/joshua/tmp/plastid-upload/plastid/kent/src/htslib/cram/open_trace_file.c
/home/joshua/tmp/plastid-upload/plastid/kent/src/htslib/cram/pooled_alloc.c
/home/joshua/tmp/plastid-upload/plastid/kent/src/htslib/cram/rANS_static.c
/home/joshua/tmp/plastid-upload/plastid/kent/src/htslib/cram/sam_header.c
/home/joshua/tmp/plastid-upload/plastid/kent/src/htslib/cram/string_alloc.c
/home/joshua/tmp/plastid-upload/plastid/kent/src/htslib/cram/thread_pool.c
/home/joshua/tmp/plastid-upload/plastid/kent/src/htslib/cram/vlen.c
/home/joshua/tmp/plastid-upload/plastid/kent/src/htslib/cram/zfio.c
/home/joshua/tmp/plastid-upload/plastid/kent/src/lib/aliType.c
plastid.egg-info/PKG-INFO
plastid.egg-info/SOURCES.txt
plastid.egg-info/dependency_links.txt
plastid.egg-info/entry_points.txt
plastid.egg-info/not-zip-safe
plastid.egg-info/requires.txt
plastid.egg-info/top_level.txt
