Metadata-Version: 2.1
Name: plastid
Version: 0.6.1
Summary: Tools for analysis of genomics & sequencing data
Home-page: https://github.com/joshuagryphon/plastid
Author: Joshua Griffin Dunn
Author-email: joshua.g.dunn@gmail.com
Maintainer: Joshua Griffin Dunn
Maintainer-email: joshua.g.dunn@gmail.com
License: BSD 3-Clause
Download-URL: https://pypi.python.org/pypi/plastid/
Keywords: ribosome profiling riboseq rna-seq sequencing genomics biology
Platform: OS Independent
Classifier: Development Status :: 5 - Production/Stable
Classifier: Programming Language :: Python :: 3.6
Classifier: Programming Language :: Python :: 3.9
Classifier: Topic :: Scientific/Engineering :: Bio-Informatics
Classifier: Topic :: Software Development :: Libraries
Classifier: Intended Audience :: Science/Research
Classifier: Intended Audience :: Developers
Classifier: License :: OSI Approved :: BSD License
Classifier: Operating System :: POSIX
Classifier: Natural Language :: English
